prophetess_salesforce/__init__.py
prophetess_salesforce/client.py
prophetess_salesforce/exceptions.py
prophetess_salesforce/extractor.py
tests/__init__.py
tests/test_client.py
tests/test_extractor.py
prophetess_salesforce-1.1.1.dist-info/LICENSE
prophetess_salesforce-1.1.1.dist-info/METADATA
prophetess_salesforce-1.1.1.dist-info/WHEEL
prophetess_salesforce-1.1.1.dist-info/entry_points.txt
prophetess_salesforce-1.1.1.dist-info/top_level.txt
prophetess_salesforce-1.1.1.dist-info/RECORD
